ai_security/__init__.py
ai_security-0.0.1.dist-info/METADATA
ai_security-0.0.1.dist-info/WHEEL
ai_security-0.0.1.dist-info/RECORD
